{
    "acceptResponse" : [
        {
            "acceptText" : "Wow! Thanks! I love my new {1}.",
            "expObjName" : "{1}"
        }
    ],
    "rejectResponse" : [
        {
            "rejectText" : "Thats weird. It looks like a {2}. I expected {1} instead",
            "expObjName" : "{1}",
            "acqObjName" : "{2}"
        }
    ],
    "request" : [
    {
        "requestText" : "Can I have shirt please?",
        "objType" : "top"
    },
    {
        "requestText" : "HELP! I need trousers.",
        "objType" : "trousers"
    },
    {
        "requestText" : "Once my pants were on fire. Now they are gone.",
        "objType" : "trousers"
    },
    {
        "requestText" : "Shibbedy shirt please",
        "objType" : "top"
    },
    {
        "requestText" : "Not only shartless but shirtless. Please fix one of those",
        "objType" : "top"
    }
    ]
}